{
    "include": [
        {
            "name": "PyCoal",
            "mods": [
                "pycoalprocessing", 
                "pycoalprocessinggraphics",
                "pypostprocessing"
            ]
        },
        {
            "name": "PyCoal, PyInd",
            "mods": [
                "pycoalprocessing", 
                "pycoalprocessinggraphics", 
                "pyindustry",
                "pypostprocessing"
            ]
        },
        {
            "name": "PyFE",
            "mods": [
                "pycoalprocessing", 
                "pycoalprocessinggraphics", 
                "pyfusionenergy",
                "pyfusionenergygraphics",
                "pypostprocessing"
            ]
        },
        {
            "name": "PyFE, PyInd",
            "mods": [
                "pycoalprocessing",
                "pycoalprocessinggraphics",
                "pyindustry",
                "pyfusionenergy",
                "pyfusionenergygraphics",
                "pypostprocessing"
            ]
        },
        {
            "name": "PyHT",
            "mods": [
                "pycoalprocessing",
                "pycoalprocessinggraphics",
                "pyindustry",
                "pyfusionenergy",
                "pyfusionenergygraphics",
                "pyhightech",
                "pyhightechgraphics",
                "pypostprocessing"
            ]
        },
        {
            "name": "PyRO",
            "mods": [
                "pycoalprocessing",
                "pycoalprocessinggraphics",
                "pyindustry",
                "pyrawores",
                "pyraworesgraphics",
                "pypostprocessing"
            ]
        },
        {
            "name": "PyRO, PyFE",
            "mods": [
                "pycoalprocessing",
                "pycoalprocessinggraphics",
                "pyindustry",
                "pyfusionenergy",
                "pyfusionenergygraphics",
                "pyrawores",
                "pyraworesgraphics",
                "pypostprocessing"
            ]
        },
        {
            "name": "PyRO, PyHT",
            "mods": [
                "pycoalprocessing",
                "pycoalprocessinggraphics",
                "pyindustry",
                "pyfusionenergy",
                "pyfusionenergygraphics",
                "pyhightech",
                "pyhightechgraphics",
                "pyrawores",
                "pyraworesgraphics",
                "pypostprocessing"
            ]
        },
        {
            "name": "PyPH",
            "mods": [
                "pycoalprocessing",
                "pycoalprocessinggraphics",
                "pyindustry",
                "pyfusionenergy",
                "pyfusionenergygraphics",
                "pypetroleumhandling",
                "pypetroleumhandlinggraphics",
                "pypostprocessing"
            ]
        },
        {
            "name": "PyPH, PyHT",
            "mods": [
                "pycoalprocessing",
                "pycoalprocessinggraphics",
                "pyindustry",
                "pyfusionenergy",
                "pyfusionenergygraphics",
                "pyhightech",
                "pyhightechgraphics",
                "pypetroleumhandling",
                "pypetroleumhandlinggraphics",
                "pypostprocessing"
            ]
        },
        {
            "name": "PyPH, PyRO",
            "mods": [
                "pycoalprocessing",
                "pycoalprocessinggraphics",
                "pyindustry",
                "pyfusionenergy",
                "pyfusionenergygraphics",
                "pyrawores",
                "pyraworesgraphics",
                "pypetroleumhandling",
                "pypetroleumhandlinggraphics",
                "pypostprocessing"
            ]
        },
        {
            "name": "PyPH, PyRO, PyHT",
            "mods": [
                "pycoalprocessing",
                "pycoalprocessinggraphics",
                "pyindustry",
                "pyfusionenergy",
                "pyfusionenergygraphics",
                "pyhightech",
                "pyhightechgraphics",
                "pyrawores",
                "pyraworesgraphics",
                "pypetroleumhandling",
                "pypetroleumhandlinggraphics",
                "pypostprocessing"
            ]
        },
        {
            "name": "PyAl",
            "mods": [
                "pycoalprocessing",
                "pycoalprocessinggraphics",
                "pyindustry",
                "pyfusionenergy",
                "pyfusionenergygraphics",
                "pyrawores",
                "pyraworesgraphics",
                "pypetroleumhandling",
                "pypetroleumhandlinggraphics",
                "pyalienlife",
                "pyalienlifegraphics",
                "pyalienlifegraphics2",
                "pyalienlifegraphics3",
                "pypostprocessing"
            ]
        },
        {
            "name": "PyAl, PyHT",
            "mods": [
                "pycoalprocessing",
                "pycoalprocessinggraphics",
                "pyindustry",
                "pyfusionenergy",
                "pyfusionenergygraphics",
                "pyhightech",
                "pyhightechgraphics",
                "pyrawores",
                "pyraworesgraphics",
                "pypetroleumhandling",
                "pypetroleumhandlinggraphics",
                "pyalienlife",
                "pyalienlifegraphics",
                "pyalienlifegraphics2",
                "pyalienlifegraphics3",
                "pypostprocessing"
            ]
        },
        {
            "name": "PyAE",
            "mods": [
                "pycoalprocessing",
                "pycoalprocessinggraphics",
                "pyindustry",
                "pyfusionenergy",
                "pyfusionenergygraphics",
                "pyhightech",
                "pyhightechgraphics",
                "pyrawores",
                "pyraworesgraphics",
                "pypetroleumhandling",
                "pypetroleumhandlinggraphics",
                "pyalienlife",
                "pyalienlifegraphics",
                "pyalienlifegraphics2",
                "pyalienlifegraphics3",
                "pyalternativeenergy",
                "pyalternativeenergygraphics",
                "pypostprocessing"
            ]
        }
    ]
}